glm_py.libs/libXpm-13335aba.so.4
glm_py.libs/libaec-ec817da7.so.0
glm_py.libs/libbz2-738ca772.so.1.0.6
glm_py.libs/libcom_err-057ba42b.so.2.1
glm_py.libs/libcrypt-0c699207.so.1
glm_py.libs/libcrypto-13880bfc.so.1.0.2k
glm_py.libs/libcurl-8621226d.so.4.3.0
glm_py.libs/libfontconfig-a93b6030.so.1.11.1
glm_py.libs/libfreetype-eea08430.so.6.14.0
glm_py.libs/libgd-23979cfe.so.2
glm_py.libs/libgfortran-daac5196.so.5.0.0
glm_py.libs/libgomp-d22c30c5.so.1.0.0
glm_py.libs/libgssapi_krb5-fec99a71.so.2.2
glm_py.libs/libhdf5-a799b2d6.so.8
glm_py.libs/libhdf5_hl-780bc0da.so.8
glm_py.libs/libidn-4bfaaf1f.so.11.6.11
glm_py.libs/libjpeg-9d1b730e.so.62
glm_py.libs/libk5crypto-47ac5e52.so.3.1
glm_py.libs/libkeyutils-19c64d08.so.1.5
glm_py.libs/libkrb5-90a0ef7c.so.3.3
glm_py.libs/libkrb5support-73f3f43d.so.0.1
glm_py.libs/liblber-2-433b48b4.4.so.2.10.7
glm_py.libs/libldap-2-333d493c.4.so.2.10.7
glm_py.libs/libnetcdf-8e8285b9.so.7
glm_py.libs/libnspr4-4b3123d9.so
glm_py.libs/libnss3-f7f80d44.so
glm_py.libs/libnssutil3-fc6773d9.so
glm_py.libs/libpcre-6b975b27.so.1.2.0
glm_py.libs/libplc4-92bde776.so
glm_py.libs/libplds4-41d879cc.so
glm_py.libs/libpng15-7864b8f1.so.15
glm_py.libs/libsasl2-6ece1dc8.so.3.0.0
glm_py.libs/libselinux-ae24b712.so.1
glm_py.libs/libsmime3-04f31a05.so
glm_py.libs/libssh2-1f2208f4.so.1.0.1
glm_py.libs/libssl-e50c59ab.so.1.0.2k
glm_py.libs/libssl3-65982fa5.so
glm_py.libs/libsz-63358849.so.2
glm_py.libs/libuuid-330f215f.so.1.3.0
glmpy/__init__.py
glmpy/_version.py
glmpy/dimensions.py
glmpy/flows.py
glmpy/glmpy.c
glmpy/plots.py
glmpy/simulation.py
glmpy/bin/glm
glmpy/data/__init__.py
glmpy/data/example_sims/__init__.py
glmpy/data/example_sims/falling_creek_reservoir.glmpy
glmpy/data/example_sims/grosse_dhuenn.glmpy
glmpy/data/example_sims/sparkling_lake.glmpy
glmpy/data/example_sims/warm_lake.glmpy
glmpy/data/example_sims/woods_lake.glmpy
glmpy/nml/__init__.py
glmpy/nml/aed_nml.py
glmpy/nml/glm_nml.py
glm_py-0.5.0.dist-info/METADATA
glm_py-0.5.0.dist-info/WHEEL
glm_py-0.5.0.dist-info/top_level.txt
glm_py-0.5.0.dist-info/RECORD
glm_py-0.5.0.dist-info/licenses/LICENSE
