Metadata-Version: 2.4
Name: glm-py
Version: 0.5.0
Summary: Python API for the General Lake Model (GLM).
License:                     GNU GENERAL PUBLIC LICENSE
Project-URL: Repository, https://github.com/AquaticEcoDynamics/glm-py
Keywords: GLM,Lake,Model
Classifier: Programming Language :: Python
Classifier: Programming Language :: Python :: 3
Requires-Python: >=3.9
License-File: LICENSE
Requires-Dist: pandas>=2.0.0
Requires-Dist: numpy>=1.26
Requires-Dist: python-multipart
Requires-Dist: netcdf4>=1.7.1.post2
Requires-Dist: matplotlib>=3.9.0
Requires-Dist: f90nml>=1.4.5
Provides-Extra: toml
Requires-Dist: tomli; python_version < "3.11" and extra == "toml"
Dynamic: license-file
